scidbstrm/__init__.py
scidb_strm-19.11.4.dist-info/LICENSE.txt
scidb_strm-19.11.4.dist-info/METADATA
scidb_strm-19.11.4.dist-info/WHEEL
scidb_strm-19.11.4.dist-info/top_level.txt
scidb_strm-19.11.4.dist-info/RECORD
