Metadata-Version: 2.1
Name: scidb-strm
Version: 19.11.4
Summary: Python library for SciDB streaming
Home-page: UNKNOWN
Author: Rares Vernica
Author-email: rvernica@gmail.com
License: AGPL-3.0
Download-URL: http://github.com/Paradigm4/Stream
Platform: UNKNOWN
Classifier: Development Status :: 4 - Beta
Classifier: Environment :: Console
Classifier: Intended Audience :: Science/Research
Classifier: License :: OSI Approved :: GNU Affero General Public License v3
Classifier: Natural Language :: English
Classifier: Programming Language :: Python :: 3.6
Classifier: Programming Language :: Python :: 3.7
Classifier: Programming Language :: Python :: 3.8
Classifier: Programming Language :: Python :: 3.9
Classifier: Programming Language :: Python :: 3.10
Classifier: Topic :: Database :: Front-Ends
Classifier: Topic :: Scientific/Engineering
License-File: LICENSE.txt
Requires-Dist: dill
Requires-Dist: pandas (>=0.20.0)
Requires-Dist: pyarrow (<=11.0.0,>=5.0.0)
